gameplus/__init__.py
gameplus-0.0.1.dist-info/LICENSE
gameplus-0.0.1.dist-info/METADATA
gameplus-0.0.1.dist-info/WHEEL
gameplus-0.0.1.dist-info/top_level.txt
gameplus-0.0.1.dist-info/RECORD
